srag/__init__.py
srag/_base.py
srag/agent/__init__.py
srag/agent/agent.py
srag/chunking/_base.py
srag/chunking/markdown.py
srag/document/__init__.py
srag/document/document.py
srag/document/index/__init__.py
srag/document/index/_base.py
srag/document/index/elastic_search.py
srag/document/index/keywords.py
srag/document/index/vector_store.py
srag/document/retriever/__init__.py
srag/document/retriever/_base.py
srag/exceptions.py
srag/llm/__init__.py
srag/llm/message.py
srag/parser/_base.py
srag/parser/pyparse.py
srag/pipeline/__init__.py
srag/pipeline/_consts.py
srag/pipeline/pipeline.py
srag/pipeline/vanilla/__init__.py
srag/pipeline/vanilla/listener.py
srag/pipeline/vanilla/trans.py
srag/pipeline/vanilla/vanilla.py
srag/utils/__init__.py
srag/utils/postprocessing/__init__.py
srag/utils/postprocessing/json.py
srag/utils/time.py
srag-0.4.1.dist-info/METADATA
srag-0.4.1.dist-info/WHEEL
srag-0.4.1.dist-info/RECORD
